test1_poetry_package/copy_df.py
test1_poetry_package-0.1.0.dist-info/WHEEL
test1_poetry_package-0.1.0.dist-info/METADATA
test1_poetry_package-0.1.0.dist-info/RECORD
