Metadata-Version: 2.1
Name: test1-poetry-package
Version: 0.1.0
Summary: 
Author: John Cummings
Author-email: johncummings@mtech-systems.com
Requires-Python: >=3.8.1,<4.0
Classifier: Programming Language :: Python :: 3
Classifier: Programming Language :: Python :: 3.9
Classifier: Programming Language :: Python :: 3.10
Classifier: Programming Language :: Python :: 3.11
Requires-Dist: pandas (>=1.5.3,<2.0.0)
Requires-Dist: pendulum (>=2.1.2,<3.0.0)
